aperturelib/__init__.py
aperturelib/resize.py
aperturelib/watermark.py
aperturelib/resources/fonts/SourceSansPro-Regular.ttf
aperturelib-1.0.0.dist-info/METADATA
aperturelib-1.0.0.dist-info/RECORD
aperturelib-1.0.0.dist-info/WHEEL
aperturelib-1.0.0.dist-info/top_level.txt
