Metadata-Version: 2.1
Name: aperturelib
Version: 1.0.0
Summary: A library for image re-sizing and compression.
Home-page: https://github.com/Aperture-py/aperture-lib
Author: salvatorej1@wit.edu, kennedyd3@wit.edu, robbinsa@wit.edu
Author-email: UNKNOWN
License: MIT License
Requires-Dist: Pillow (==5.0.0)
